jupyrest/__init__.py
jupyrest/client.py
jupyrest/contracts.py
jupyrest/default_impl/__init__.py
jupyrest/default_impl/builder.py
jupyrest/default_impl/execution_task_handler.py
jupyrest/default_impl/executor.py
jupyrest/default_impl/file_namer.py
jupyrest/default_impl/input_output_validator.py
jupyrest/default_impl/notebook_converter.py
jupyrest/default_impl/notebook_repository.py
jupyrest/default_impl/output_reader.py
jupyrest/default_impl/parameterizer.py
jupyrest/error.py
jupyrest/file_object.py
jupyrest/http/__init__.py
jupyrest/http/asgi.py
jupyrest/http/models.py
jupyrest/infra/__init__.py
jupyrest/infra/azure/__init__.py
jupyrest/infra/azure/builder.py
jupyrest/infra/azure/execution_repository.py
jupyrest/infra/azure/execution_task_handler.py
jupyrest/infra/azure/file_object_client.py
jupyrest/infra/in_memory/__init__.py
jupyrest/infra/in_memory/builder.py
jupyrest/infra/in_memory/execution_repository.py
jupyrest/infra/in_memory/file_object_client.py
jupyrest/model.py
jupyrest/nbschema.py
jupyrest/notebook_config.py
jupyrest/notebook_execution/commands.py
jupyrest/notebook_execution/common.py
jupyrest/notebook_execution/entity.py
jupyrest/notebook_execution/queries.py
jupyrest-0.2.0.dist-info/METADATA
jupyrest-0.2.0.dist-info/WHEEL
jupyrest-0.2.0.dist-info/RECORD
